Metadata-Version: 2.1
Name: noticeme
Version: 2019.11
Summary: Provides a framework for building file watchers. Includes a file watcher utility program that allows you to create file watchers declaratively.
Home-page: https://github.com/bobbytrapz/noticeme
Author: Bobby
Author-email: bobbytrapz@protonmail.com
License: MIT
Keywords: inotify watch development
Platform: UNKNOWN
Classifier: Development Status :: 4 - Beta
Classifier: License :: OSI Approved :: MIT License
Classifier: Operating System :: POSIX :: Linux
Classifier: Programming Language :: Python :: 3.5
Classifier: Topic :: Software Development :: Build Tools
Classifier: Topic :: System :: Filesystems
Requires-Python: >=3.5
